LICENSE
MANIFEST.in
README.md
setup.py
chhuang789/__init__.py
chhuang789/__version__.py
chhuang789/core.py
chhuang789/main.py
chhuang789.egg-info/PKG-INFO
chhuang789.egg-info/SOURCES.txt
chhuang789.egg-info/dependency_links.txt
chhuang789.egg-info/top_level.txt