Metadata-Version: 2.1
Name: chhuang789
Version: 0.1.0
Summary: This is my first project for python package.
Home-page: https://github.com/chhuang789/chhuang789
Author: C.H. Huang
Author-email: chhuang789@gmail.com
License: MIT
Platform: UNKNOWN
Classifier: License :: OSI Approved :: MIT License
Classifier: Programming Language :: Python
Classifier: Programming Language :: Python :: 3
Classifier: Programming Language :: Python :: 3.6
Classifier: Programming Language :: Python :: Implementation :: CPython
Classifier: Programming Language :: Python :: Implementation :: PyPy
Requires-Python: >=3.6.0
License-File: LICENSE
